LICENSE
README.rst
setup.cfg
setup.py
workbench/__init__.py
workbench/context_processors.py
workbench/factories.py
workbench/generic.py
workbench/middleware.py
workbench/settings.py
workbench/test_history.py
workbench/test_redirects.py
workbench/test_search.py
workbench/test_templatetags.py
workbench/test_tools.py
workbench/urls.py
workbench/views.py
workbench/wrappers.py
workbench/accounts/__init__.py
workbench/accounts/admin.py
workbench/accounts/backends.py
workbench/accounts/features.py
workbench/accounts/forms.py
workbench/accounts/middleware.py
workbench/accounts/models.py
workbench/accounts/reporting.py
workbench/accounts/test_accounts.py
workbench/accounts/test_login.py
workbench/accounts/urls.py
workbench/accounts/views.py
workbench/accounts/migrations/0001_initial.py
workbench/accounts/migrations/0002_auto_20190304_2247.py
workbench/accounts/migrations/0003_user_enforce_same_week_logging.py
workbench/accounts/migrations/0004_user_language.py
workbench/accounts/migrations/0005_user_working_time_model.py
workbench/accounts/migrations/0006_auto_20191207_1307.py
workbench/accounts/migrations/0007_team.py
workbench/accounts/migrations/0008_auto_20200114_0757.py
workbench/accounts/migrations/0009_user_person.py
workbench/accounts/migrations/0010_auto_20201016_0957.py
workbench/accounts/migrations/0011_auto_20201017_1018.py
workbench/accounts/migrations/0012_user_planning_hours_per_day.py
workbench/accounts/migrations/__init__.py
workbench/audit/__init__.py
workbench/audit/admin.py
workbench/audit/models.py
workbench/audit/test_admin.py
workbench/audit/migrations/0001_initial.py
workbench/audit/migrations/0002_auto_20190321_1626.py
workbench/audit/migrations/0003_auto_20190703_0813.py
workbench/audit/migrations/0004_auto_20201017_1016.py
workbench/audit/migrations/__init__.py
workbench/awt/__init__.py
workbench/awt/admin.py
workbench/awt/forms.py
workbench/awt/models.py
workbench/awt/pdf.py
workbench/awt/reporting.py
workbench/awt/test_awt.py
workbench_crm.egg-info/PKG-INFO
workbench_crm.egg-info/SOURCES.txt
workbench_crm.egg-info/dependency_links.txt
workbench_crm.egg-info/not-zip-safe
workbench_crm.egg-info/top_level.txt