Metadata-Version: 2.1
Name: workbench-crm
Version: 0.0.20210124
Summary: Django-based Agency Software (time tracking, project management, addressbook, offering and invoicing)
Home-page: https://github.com/matthiask/workbench/
Author: Matthias Kestenholz
Author-email: mk@feinheit.ch
License: MIT
Platform: OS Independent
Classifier: Environment :: Web Environment
Classifier: Framework :: Django
Classifier: Intended Audience :: Developers
Classifier: License :: OSI Approved :: MIT License
Classifier: Operating System :: OS Independent
Classifier: Programming Language :: Python
Classifier: Programming Language :: Python :: 3
Classifier: Programming Language :: Python :: 3 :: Only
Classifier: Programming Language :: Python :: 3.8
Classifier: Programming Language :: Python :: 3.9
Requires-Python: >=3.8
